LICENSE
README.md
setup.py
clastline/__init__.py
clastline/test_clastline.py
clastline.egg-info/PKG-INFO
clastline.egg-info/SOURCES.txt
clastline.egg-info/dependency_links.txt
clastline.egg-info/top_level.txt