Metadata-Version: 2.1
Name: clastline
Version: 2.0.0
Home-page: http://github.com/csm10495/clastline
Author: csm10495
Author-email: csm10495@gmail.com
License: MIT License
Classifier: Intended Audience :: Developers
Classifier: Natural Language :: English
Classifier: Operating System :: Microsoft :: Windows
Classifier: Programming Language :: Python
Classifier: Programming Language :: Python :: 3
Requires-Python: >=3.6
License-File: LICENSE
